pypi_changes/__init__.py
pypi_changes/__main__.py
pypi_changes/_cli.py
pypi_changes/_distributions.py
pypi_changes/_info.py
pypi_changes/_pkg.py
pypi_changes/_version.py
pypi_changes/py.typed
pypi_changes/_print/__init__.py
pypi_changes/_print/json.py
pypi_changes/_print/tree.py
pypi_changes-1.4.0.dist-info/METADATA
pypi_changes-1.4.0.dist-info/WHEEL
pypi_changes-1.4.0.dist-info/entry_points.txt
pypi_changes-1.4.0.dist-info/licenses/LICENSE
pypi_changes-1.4.0.dist-info/RECORD
