Metadata-Version: 2.4
Name: pypi-changes
Version: 1.4.0
Summary: check out when packages changed
Project-URL: Homepage, https://github.com/gaborbernat/pypi_changes
Project-URL: Source, https://github.com/gaborbernat/pypi_changes
Project-URL: Tracker, https://github.com/gaborbernat/pypi_changes/issues
Author-email: Bernát Gábor <gaborjbernat@gmail.com>
Maintainer-email: Bernát Gábor <gaborjbernat@gmail.com>
License-Expression: MIT
License-File: LICENSE
Keywords: environments,isolated,testing,virtual
Classifier: Development Status :: 5 - Production/Stable
Classifier: Framework :: tox
Classifier: Intended Audience :: Developers
Classifier: License :: OSI Approved :: MIT License
Classifier: Operating System :: MacOS :: MacOS X
Classifier: Operating System :: Microsoft :: Windows
Classifier: Operating System :: POSIX
Classifier: Programming Language :: Python :: 3 :: Only
Classifier: Programming Language :: Python :: 3.9
Classifier: Programming Language :: Python :: 3.10
Classifier: Programming Language :: Python :: 3.11
Classifier: Programming Language :: Python :: 3.12
Classifier: Programming Language :: Python :: 3.13
Classifier: Programming Language :: Python :: 3.14
Classifier: Topic :: Software Development :: Libraries
Classifier: Topic :: Software Development :: Testing
Classifier: Topic :: Utilities
Requires-Python: >=3.9
Requires-Dist: humanize>=4.13
Requires-Dist: packaging>=25
Requires-Dist: platformdirs>=4.4
Requires-Dist: pypi-simple>=1.8
Requires-Dist: requests-cache>=1.2.1
Requires-Dist: requests>=2.32.5
Requires-Dist: rich>=14.1
Provides-Extra: testing
Requires-Dist: covdefaults>=2.3; extra == 'testing'
Requires-Dist: pytest-cov>=7; extra == 'testing'
Requires-Dist: pytest-mock>=3.15.1; extra == 'testing'
Requires-Dist: pytest>=8.4.2; extra == 'testing'
Requires-Dist: urllib3<2; extra == 'testing'
Requires-Dist: vcrpy>=7; extra == 'testing'
Requires-Dist: virtualenv>=20.34; extra == 'testing'
